shrug/__init__.py
shrug/cli.py
shrug-0.1.1.dist-info/LICENSE.txt
shrug-0.1.1.dist-info/METADATA
shrug-0.1.1.dist-info/RECORD
shrug-0.1.1.dist-info/WHEEL
shrug-0.1.1.dist-info/entry_points.txt
shrug-0.1.1.dist-info/top_level.txt
