Metadata-Version: 2.1
Name: shrug
Version: 0.1.1
Summary: Shrug emoticon printer
Home-page: https://github.com/Necior/shrug
Author: Adrian Sadłocha
Author-email: UNKNOWN
License: UNKNOWN
Platform: UNKNOWN
